odoo/addons/sale_report_delivered_brand/README.rst
odoo/addons/sale_report_delivered_brand/__init__.py
odoo/addons/sale_report_delivered_brand/__manifest__.py
odoo/addons/sale_report_delivered_brand/i18n/es.po
odoo/addons/sale_report_delivered_brand/i18n/sale_report_delivered_brand.pot
odoo/addons/sale_report_delivered_brand/models/__init__.py
odoo/addons/sale_report_delivered_brand/models/sale_report_delivered.py
odoo/addons/sale_report_delivered_brand/readme/CONTRIBUTORS.rst
odoo/addons/sale_report_delivered_brand/readme/DESCRIPTION.rst
odoo/addons/sale_report_delivered_brand/readme/USAGE.rst
odoo/addons/sale_report_delivered_brand/static/description/icon.png
odoo/addons/sale_report_delivered_brand/static/description/index.html
odoo/addons/sale_report_delivered_brand/views/sale_report_delivered_views.xml
odoo13_addon_sale_report_delivered_brand-13.0.1.0.1.dev5.dist-info/METADATA
odoo13_addon_sale_report_delivered_brand-13.0.1.0.1.dev5.dist-info/WHEEL
odoo13_addon_sale_report_delivered_brand-13.0.1.0.1.dev5.dist-info/top_level.txt
odoo13_addon_sale_report_delivered_brand-13.0.1.0.1.dev5.dist-info/RECORD
